mseep_thingspanel_mcp-0.1.8.dist-info/licenses/LICENSE
thingspanel_mcp/__init__.py
thingspanel_mcp/api_client.py
thingspanel_mcp/config.py
thingspanel_mcp/main.py
thingspanel_mcp/server.py
thingspanel_mcp/prompts/__init__.py
thingspanel_mcp/prompts/common_prompts.py
thingspanel_mcp/tools/__init__.py
thingspanel_mcp/tools/control_tools.py
thingspanel_mcp/tools/dashboard_tools.py
thingspanel_mcp/tools/device_tools.py
thingspanel_mcp/tools/telemetry_tools.py
mseep_thingspanel_mcp-0.1.8.dist-info/METADATA
mseep_thingspanel_mcp-0.1.8.dist-info/WHEEL
mseep_thingspanel_mcp-0.1.8.dist-info/entry_points.txt
mseep_thingspanel_mcp-0.1.8.dist-info/top_level.txt
mseep_thingspanel_mcp-0.1.8.dist-info/RECORD
