Metadata-Version: 2.4
Name: mseep-thingspanel-mcp
Version: 0.1.8
Summary: MCP server for ThingsPanel IoT platform
Author-email: mseep <support@skydeck.ai>
License:                                  Apache License
Project-URL: Homepage, https://github.com/ThingsPanel/thingspanel-mcp
Classifier: Programming Language :: Python :: 3
Classifier: License :: OSI Approved :: MIT License
Classifier: Operating System :: OS Independent
Requires-Python: >=3.8
License-File: LICENSE
Requires-Dist: mcp>=1.2.0
Requires-Dist: httpx>=0.23.0
Dynamic: license-file
